gpt_trainer/__init__.py
gpt_trainer/api.py
gpt_trainer/base.py
gpt_trainer/agent/__init__.py
gpt_trainer/agent/agent_api.py
gpt_trainer/agent/agent_models.py
gpt_trainer/agent/agent_properties.py
gpt_trainer/chatbot/__init__.py
gpt_trainer/chatbot/chatbot_api.py
gpt_trainer/chatbot/chatbot_models.py
gpt_trainer/chatbot/chatbot_properties.py
gpt_trainer/data_source/__init__.py
gpt_trainer/data_source/data_source_tag_api.py
gpt_trainer/data_source/source_api.py
gpt_trainer/data_source/source_models.py
gpt_trainer/data_source/source_properties.py
gpt_trainer/session/__init__.py
gpt_trainer/session/message_api.py
gpt_trainer/session/message_models.py
gpt_trainer/session/message_properties.py
gpt_trainer/session/session_api.py
gpt_trainer/session/session_models.py
gpt_trainer/session/session_properties.py
tests/__init__.py
tests/conftest.py
tests/test_agent.py
tests/test_chatbot.py
tests/test_data_source.py
tests/test_message.py
tests/test_session.py
gpt_trainer_api-0.2.3.dist-info/LICENSE
gpt_trainer_api-0.2.3.dist-info/METADATA
gpt_trainer_api-0.2.3.dist-info/WHEEL
gpt_trainer_api-0.2.3.dist-info/top_level.txt
gpt_trainer_api-0.2.3.dist-info/RECORD
