Metadata-Version: 2.2
Name: gpt_trainer_api
Version: 0.2.3
Summary: Python client for interacting with the GPT Trainer API.
Home-page: https://github.com/Tahir-Siddique/gpt-trainer-api
Author: Tahir Siddique
Author-email: tahirsiddiquework@gmail.com
Project-URL: Source, https://github.com/Tahir-Siddique/gpt-trainer-api
Project-URL: Tracker, https://github.com/Tahir-Siddique/gpt-trainer-api/issues
Classifier: Programming Language :: Python :: 3.7
Classifier: Programming Language :: Python :: 3.8
Classifier: Programming Language :: Python :: 3.9
Classifier: Programming Language :: Python :: 3.10
Classifier: License :: OSI Approved :: MIT License
Classifier: Operating System :: OS Independent
Requires-Python: >=3.7
License-File: LICENSE
Requires-Dist: requests>=2.32.3
Dynamic: author
Dynamic: author-email
Dynamic: classifier
Dynamic: description
Dynamic: description-content-type
Dynamic: home-page
Dynamic: project-url
Dynamic: requires-dist
Dynamic: requires-python
Dynamic: summary
